pollination/direct_sun_hours/__init__.py
pollination/direct_sun_hours/entry.py
pollination_direct_sun_hours.express-0.5.30.dist-info/LICENSE
pollination_direct_sun_hours.express-0.5.30.dist-info/METADATA
pollination_direct_sun_hours.express-0.5.30.dist-info/WHEEL
pollination_direct_sun_hours.express-0.5.30.dist-info/top_level.txt
pollination_direct_sun_hours.express-0.5.30.dist-info/RECORD
