Metadata-Version: 2.1
Name: pollination-direct-sun-hours.express
Version: 0.5.30
Summary: Direct sun hours recipe for Pollination.
Home-page: https://github.com/pollination/direct-sun-hours
Author: ladybug-tools
Author-email: info@ladybug.tools
Maintainer: mostapha, ladybug-tools
Maintainer-email: mostapha@ladybug.tools, info@ladybug.tools
License: PolyForm Shield License 1.0.0, https://polyformproject.org/wp-content/uploads/2020/06/PolyForm-Shield-1.0.0.txt
Project-URL: icon, https://raw.githubusercontent.com/ladybug-tools/artwork/master/icons_components/honeybee/png/directsun.png
Project-URL: docker, https://hub.docker.com/r/ladybugtools/honeybee-radiance
Keywords: honeybee,radiance,ladybug-tools,daylight,direct-sun-hours
License-File: LICENSE
Requires-Dist: pollination-ladybug-radiance>=0.2.3
Provides-Extra: viz
Requires-Dist: pollination-honeybee-display>=0.1.19; extra == "viz"
